{
  "new_report":"New report",
  "continue":"Continuare",
  "login": "Authenticate",
  "register": "Submit Registration",
  "back":"Înapoi",
  "yes":"Yes",
  "no":"No",
  "pdf_download":"Trimite ALERTĂ",
  "finish":"Done",
  "submit":"Submit",
  "warning":"Please fill out all asked fields.",
  "field_warning":"Please fill out this field.",
  "wrong_time_warning":"Please enter the incident date.",
  "gdpr_accept":"Accept",
  "gdpr_warning":"Please agree with GDPR agreement.",
  "no_results": "No results.",
  "complete_registration_string": "Complete Registration",
  "summary":"Rezumat ALERTĂ",
  "done":"DONE",
  "satisfied_recommendation":"If you are satisfied with the recommendations click Done.",
  "recommendation":"Recomandări",
  "no_recommendation":"No Matching Recommendations",
  "no_recommendation_case":"Nici o recomandare pentru acest caz",
  "no_user":"No Such User",
  "register_now": "Neînregistrat? Înregistrați-vă acum!",
  "register_btn": "Înegistrare",
  "alert_report": "ALERT REPORT",
  "country": "Register",
  "city": "Register",
  "time": "Register",
  "alert_category": "Alert Category",
  "alert_location": "Alert Location",
  "alert_target": "Alert Target",
  "subject": "Subject",
  "description": "Description",
  "review_data": "vă rugăm să revizuiți datele dvs.",
  "other": "Altele",
  "registration_confirmed": "Înregistrare confirmată",
  "your_registration_confirmed": "Yînregistrarea noastră a fost confirmată. Vă veți putea conecta odată ce Moderatorul va accepta solicitarea.",
  "verification_code": "Cod de verificare",
  "your_verification_code": "Codul dvs. de verificare: ",
  "redirect": "Utilizator înregistrat. Redirecționarea înapoi la Arena. . ."
}
